speedsense/__init__.py
speedsense/benchmark_functions.py
speedsense/code_extractor.py
speedsense/function_generator.py
speedsense/tc_estimator.py
speedsense-0.2.3.dist-info/LICENSE.txt
speedsense-0.2.3.dist-info/METADATA
speedsense-0.2.3.dist-info/WHEEL
speedsense-0.2.3.dist-info/top_level.txt
speedsense-0.2.3.dist-info/RECORD
