Metadata-Version: 2.1
Name: speedsense
Version: 0.2.3
Summary: Automatic time complexity analysis with visualization for Python functions
Home-page: https://github.com/anantterkar/SpeedSense
Author: Anant Terkar
Author-email: Anant Terkar <20bcs014@iiitdwd.ac.in>
Maintainer-email: Anant Terkar <20bcs014@iiitdwd.ac.in>
License: MIT
Project-URL: Homepage, https://github.com/anantterkar/SpeedSense
Project-URL: Repository, https://github.com/anantterkar/SpeedSense
Project-URL: Bug Tracker, https://github.com/anantterkar/SpeedSense/issues
Keywords: complexity,analysis,algorithm,big-o,time-complexity,visualization
Classifier: Development Status :: 4 - Beta
Classifier: Intended Audience :: Developers
Classifier: License :: OSI Approved :: MIT License
Classifier: Programming Language :: Python :: 3
Classifier: Programming Language :: Python :: 3.8
Classifier: Programming Language :: Python :: 3.9
Classifier: Programming Language :: Python :: 3.10
Classifier: Programming Language :: Python :: 3.11
Classifier: Programming Language :: Python :: 3.12
Classifier: Topic :: Software Development :: Libraries :: Python Modules
Classifier: Topic :: Scientific/Engineering :: Information Analysis
Requires-Python: >=3.8
License-File: LICENSE.txt
Requires-Dist: matplotlib>=3.10.1
Requires-Dist: numpy>=2.2.5
Provides-Extra: dev
Requires-Dist: pytest>=8.3.5; extra == "dev"
Requires-Dist: twine>=6.1.0; extra == "dev"
